datapizza/tools/filesystem/__init__.py
datapizza/tools/filesystem/filesystem.py
datapizza_ai_tools_filesystem-0.0.2.dist-info/METADATA
datapizza_ai_tools_filesystem-0.0.2.dist-info/WHEEL
datapizza_ai_tools_filesystem-0.0.2.dist-info/RECORD
