Metadata-Version: 2.4
Name: datapizza-ai-tools-filesystem
Version: 0.0.2
Summary: A tool for interacting with the local file system.
Author-email: Nilthon Jhon Rojas Apumayta <oneill.jhon97@gmail.com>
License: MIT
Classifier: License :: OSI Approved :: MIT License
Classifier: Operating System :: OS Independent
Classifier: Programming Language :: Python :: 3
Requires-Python: <4,>=3.10.0
Requires-Dist: datapizza-ai-core<0.1.0,>=0.0.1
